{
  "basics": {
    "name": "Dylan Dela Cruz",
    "label": "Student",
    "picture": "https://github.com/loldylo.png",
    "email": "dylan65@hawaii.edu",
    "phone": "",
    "website": "https://loldylo.github.io",
    "summary": "I am studying for a B.S. in Computer Science in the Department of Information and Computer Sciences at the University of Hawaii. I expect to graduate in Spring, 2027.",
    "location": { "address": "", "postalCode": "96791", "city": "Waialua", "countryCode": "USA", "region": "Hawaii" },
    "profiles": [
      { "network": "github", "username": "loldylo", "url": "http://github.com/loldylo" },
      { "network": "linkedin", "username": "loldylo", "url": "http://linkedin.com/in/loldylo" },
      { "network": "instagram", "username": "notdylo", "url": "http://instagram.com/notdylo" }
    ]
  },
  "interests": [
    { "name": "Gym" },
    { "name": "Money" },
    { "name": "Educating" },
    { "name": "Creating" },
    { "name": "Tinkering" }
  ],
  "skills": [
    {
      "name": "Languages and Frameworks",
      "keywords": [ "C", "C++", "Java", "Javascript" ]
    },
    {
      "name": "Toolsets/OS",
      "keywords": [ "Windows", "MacOS", "Git/GitHub" ]
    }
  ],
  "education": [
    {
      "institution": "University of Hawaii, Honolulu, HI",
      "area": "Computer Science (expected Spring, 2027)",
      "studyType": "B.S.",
      "startDate": "2023-05-25",
      "endDate": "Present",
      "courses": [
      ]
    }
  ],
  "work": [
    {
      "company": "Shabuya",
      "position": "Busser",
      "website": "",
      "startDate": "2025-04-28",
      "endDate": "Present",
      "summary": "",
      "highlights": [
        "Keep the restaurant clean."
      ]
    },
    {
      "company": "UH NetOps Tech",
      "position": "NetOps Technician",
      "website": "http://www.hawaii.edu/its/",
      "startDate": "2024-05-28",
      "endDate": "present",
      "summary": "",
      "highlights": [
        "Troubleshoot software, hardware and networking issues over the phone",
        "Answer phone and email responses to the ITS Help Desk"
      ]
    }
  ],
  "volunteer": [
    {
      "organization": "Center for Renewable Energy and Island Sustainability",
      "website": "http://manoa.hawaii.edu/reis",
      "position": "Software Developer",
      "startDate": "2016-01-01",
      "endDate": "Present",
      "summary": "Lead developer for weather sensing project",
      "highlights": [
        "Design firmware for distributed weather sensor network",
        "Maintain custom data collection and storage infrastructure"
      ]
    },
    {
      "organization": "",
      "website": "",
      "position": "Professional organization involvement",
      "startDate": "",
      "endDate": "",
      "summary": "",
      "highlights": [
        "Chair, ACM Manoa, 2016-Present",
        "Member, IEEE Student Branch, 2014-Present",
        "Webmaster/IT Officer, IEEE Student Branch, UH Manoa, 2012-2013"
      ]
    }
  ],
  "awards": [
    {
      "title": "B+ Scholarship",
      "date": "2013-Present",
      "awarder": "State of Hawaii",
      "summary": "Scholarships awarded to incoming freshmen and continuing students who complete a rigorous high school curriculum with a minimum overall GPA of 3.0 at a Hawai'i public school."
    },
    {
      "title": "First place",
      "date": "2015",
      "awarder": "University of Hawaii Micromouse Competition",
      "summary": "My team won first place in 2015.  See my portfolio site for more details."
    }
  ],
  "references": [
    {
      "name": "Available upon request"
    }
  ]
}
